pyshoc/__init__.py
pyshoc/__main__.py
pyshoc/caldb.py
pyshoc/config.py
pyshoc/config.yaml
pyshoc/convert_keywords.py
pyshoc/core.py
pyshoc/flopzone.py
pyshoc/header.py
pyshoc/match.py
pyshoc/printing.py
pyshoc/tel_info.py
pyshoc/timing.py
pyshoc/treeops.py
pyshoc/utils.py
pyshoc/examples/pySHOC-demo.py
pyshoc/examples/pySHOC.demo.html
pyshoc/examples/pySHOC.demo.ipynb
pyshoc/image/__init__.py
pyshoc/image/sample.py
pyshoc/nightlog/weather.py
pyshoc/pipeline/__init__.py
pyshoc/pipeline/__main__.py
pyshoc/pipeline/calibrate.py
pyshoc/pipeline/cli.py
pyshoc/pipeline/lightcurves.py
pyshoc/pipeline/logging.py
pyshoc/pipeline/main.py
pyshoc/pipeline/plotting.py
pyshoc/pipeline/products.py
pyshoc/pipeline/run.py
pyshoc/pipeline/utils.py
pyshoc/pipeline/banner/__init__.py
pyshoc/pipeline/banner/logo.txt
pyshoc/readnoise/README
pyshoc/readnoise/__init__.py
pyshoc/readnoise/data/SHOC1.txt
pyshoc/readnoise/data/SHOC2.txt
pyshoc-1.2.0.dist-info/LICENSE
pyshoc-1.2.0.dist-info/METADATA
pyshoc-1.2.0.dist-info/WHEEL
pyshoc-1.2.0.dist-info/entry_points.txt
pyshoc-1.2.0.dist-info/top_level.txt
pyshoc-1.2.0.dist-info/RECORD
