Metadata-Version: 2.1
Name: pyshoc
Version: 1.2.0
Summary: Tools for data analysis and reduction of data from the Sutherland High Speed Optical Cameras (SHOC). 📷🔭
Author-email: Hannes Breytenbach <hannes@saao.ac.za>
License: MIT
Project-URL: Homepage, https://github.com/astromancer/pyshoc
Project-URL: Bug Tracker, https://github.com/astromancer/pyshoc/issues
Classifier: Development Status :: 4 - Beta
Classifier: Intended Audience :: Science/Research
Classifier: Intended Audience :: Education
Classifier: Programming Language :: Python :: 3.8
Classifier: License :: OSI Approved :: MIT License
Classifier: Operating System :: POSIX :: Linux
Requires-Python: >=3.8
License-File: LICENSE
Provides-Extra: tests
Requires-Dist: pytest ; extra == 'tests'
